Compiled from "ClientModBusSubscriber.java"
public class com.fluxsyum.cullify.client.ClientModBusSubscriber {
  public static net.minecraft.client.KeyMapping configKeyMapping;

  public com.fluxsyum.cullify.client.ClientModBusSubscriber();
    Code:
       0: aload_0
       1: invokespecial #1                  // Method java/lang/Object."<init>":()V
       4: return

  public static void register(net.neoforged.bus.api.IEventBus);
    Code:
       0: aload_0
       1: invokedynamic #7,  0              // InvokeDynamic #0:accept:()Ljava/util/function/Consumer;
       6: invokeinterface #11,  2           // InterfaceMethod net/neoforged/bus/api/IEventBus.addListener:(Ljava/util/function/Consumer;)V
      11: aload_0
      12: invokedynamic #17,  0             // InvokeDynamic #1:accept:()Ljava/util/function/Consumer;
      17: invokeinterface #11,  2           // InterfaceMethod net/neoforged/bus/api/IEventBus.addListener:(Ljava/util/function/Consumer;)V
      22: return

  public static void registerKeyMappings(net.neoforged.neoforge.client.event.RegisterKeyMappingsEvent);
    Code:
       0: new           #18                 // class net/minecraft/client/KeyMapping
       3: dup
       4: ldc           #20                 // String key.cullify.config
       6: bipush        75
       8: ldc           #24                 // String key.categories.cullify
      10: invokespecial #26                 // Method net/minecraft/client/KeyMapping."<init>":(Ljava/lang/String;ILjava/lang/String;)V
      13: putstatic     #29                 // Field configKeyMapping:Lnet/minecraft/client/KeyMapping;
      16: aload_0
      17: getstatic     #29                 // Field configKeyMapping:Lnet/minecraft/client/KeyMapping;
      20: invokevirtual #35                 // Method net/neoforged/neoforge/client/event/RegisterKeyMappingsEvent.register:(Lnet/minecraft/client/KeyMapping;)V
      23: return

  public static void registerGuiLayers(net.neoforged.neoforge.client.event.RegisterGuiLayersEvent);
    Code:
       0: aload_0
       1: getstatic     #41                 // Field net/neoforged/neoforge/client/gui/VanillaGuiLayers.HOTBAR:Lnet/minecraft/resources/ResourceLocation;
       4: ldc           #49                 // String cullify
       6: ldc           #51                 // String debug_hud
       8: invokestatic  #53                 // Method net/minecraft/resources/ResourceLocation.fromNamespaceAndPath:(Ljava/lang/String;Ljava/lang/String;)Lnet/minecraft/resources/ResourceLocation;
      11: invokedynamic #59,  0             // InvokeDynamic #2:render:()Lnet/minecraft/client/gui/LayeredDraw$Layer;
      16: invokevirtual #63                 // Method net/neoforged/neoforge/client/event/RegisterGuiLayersEvent.registerAbove:(Lnet/minecraft/resources/ResourceLocation;Lnet/minecraft/resources/ResourceLocation;Lnet/minecraft/client/gui/LayeredDraw$Layer;)V
      19: return

  static {};
    Code:
       0: ldc           #49                 // String cullify
       2: ldc           #201                // String textures/gui/logo.png
       4: invokestatic  #53                 // Method net/minecraft/resources/ResourceLocation.fromNamespaceAndPath:(Ljava/lang/String;Ljava/lang/String;)Lnet/minecraft/resources/ResourceLocation;
       7: putstatic     #108                // Field LOGO_RL:Lnet/minecraft/resources/ResourceLocation;
      10: return
}
